wmain/__init__.py
wmain/ext/__init__.py
wmain/ext/fastapi/__init__.py
wmain/ext/fastapi/middlewares/__init__.py
wmain/ext/fastapi/middlewares/log_middleware.py
wmain_extensions-0.1.1.dist-info/METADATA
wmain_extensions-0.1.1.dist-info/WHEEL
wmain_extensions-0.1.1.dist-info/RECORD
