Metadata-Version: 2.4
Name: wmain-extensions
Version: 0.1.1
Summary: wmain 扩展包, 仅作为其他模块例如 fastapi, sqlalchemy等的扩展,不影响wmain的使用
License: MIT
Author: wmain-extensions@wyn.wiki
Requires-Python: >=3.10,<4.0
Classifier: License :: OSI Approved :: MIT License
Classifier: Programming Language :: Python :: 3
Classifier: Programming Language :: Python :: 3.10
Classifier: Programming Language :: Python :: 3.11
Classifier: Programming Language :: Python :: 3.12
Classifier: Programming Language :: Python :: 3.13
Classifier: Programming Language :: Python :: 3.14
Requires-Dist: fastapi (>=0.124.0,<0.125.0)
Requires-Dist: starlette (>=0.50.0,<0.51.0)
Requires-Dist: wmain-base (==0.1.0)
